parampl/__init__.py
parampl/core.py
parampl/statics.py
parampl-0.3.7.dist-info/licenses/LICENSE
parampl-0.3.7.dist-info/METADATA
parampl-0.3.7.dist-info/WHEEL
parampl-0.3.7.dist-info/top_level.txt
parampl-0.3.7.dist-info/RECORD
