Metadata-Version: 2.4
Name: parampl
Version: 0.3.7
Summary: Formatting paragraphs for matplotlib text
Author-email: duckrojo <3063609+duckrojo@users.noreply.github.com>
Project-URL: Documentation, https://parampl.readthedocs.io/en/latest/
Project-URL: Repository, https://github.com/duckrojo/parampl
Requires-Python: >=3.13
License-File: LICENSE
Requires-Dist: matplotlib>=3.10.3
Dynamic: license-file
